{
  "code": 0,
  "data": {
    "aid": 14690803,
    "videos": 1,
    "tid": 172,
    "tname": "手机游戏",
    "copyright": 1,
    "pic": "http://i2.hdslb.com/bfs/archive/0c13411b9ae53ed6cac0eb392a073c0957a45865.jpg",
    "title": "【fgo】两仪式：活着的东西，就算是王哈桑，也杀给你看。",
    "pubdate": 1506074078,
    "ctime": 1506074079,
    "desc": "厨力放出A+++\n在高难度王哈桑里，也许是最华丽的抗即死和斩杀方式吧。\n\n素材处理和制作视频，\n花了非常非常多的时间，（40+小时）\n尼禄祭似乎都结束好几天了（扶额）\n算是非常迟到了。\n许多音效都是添加补录的，而且有大量剪辑。\n\n但是，希望会有人，理解我的这份感情吧。",
    "state": 0,
    "attribute": 49280,
    "tags": null,
    "duration": 255,
    "rights": {
      "bp": 0,
      "elec": 1,
      "download": 1,
      "movie": 0,
      "pay": 0,
      "hd5": 0,
      "no_reprint": 1
    },
    "owner": {
      "mid": 5243943,
      "name": "竹宫悠子",
      "face": "http://i1.hdslb.com/bfs/face/940a650d7fa6639cb1084f1bcca9d257ea2a1019.jpg"
    },
    "stat": {
      "aid": 14690803,
      "view": 107428,
      "danmaku": 610,
      "reply": 675,
      "favorite": 3819,
      "coin": 5406,
      "share": 1052,
      "now_rank": 0,
      "his_rank": 0,
      "like": 482
    },
    "pages": [
      {
        "cid": 23947539,
        "page": 1,
        "from": "vupload",
        "part": "",
        "duration": 255,
        "vid": "",
        "weblink": "",
        "metas": [
          {
            "quality": 16,
            "format": "",
            "size": 17531
          },
          {
            "quality": 32,
            "format": "",
            "size": 35062
          },
          {
            "quality": 48,
            "format": "",
            "size": 52593
          },
          {
            "quality": 64,
            "format": "",
            "size": 56100
          },
          {
            "quality": 80,
            "format": "",
            "size": 77137
          },
          {
            "quality": 112,
            "format": "",
            "size": 140250
          }
        ],
        "dmlink": "http://comment.bilibili.com/23947539.xml"
      }
    ],
    "owner_ext": {
      "vip": {
        "vipType": 1,
        "vipDueDate": 1531756800000,
        "dueRemark": "",
        "accessStatus": 1,
        "vipStatus": 1,
        "vipStatusWarn": ""
      },
      "assists": null,
      "fans": 5894,
      "archives": 18
    },
    "req_user": {
      "attention": -999,
      "favorite": 0,
      "like": 0
    },
    "tag": [
      {
        "tag_id": 23326,
        "tag_name": "两仪式",
        "cover": "http://i0.hdslb.com/bfs/tag/bf6ce00f2b0f03fce347982774b3d957702a2176.jpg",
        "likes": 4,
        "hates": 0,
        "liked": 0,
        "hated": 0,
        "attribute": 0
      },
      {
        "tag_id": 44018,
        "tag_name": "黑桐干也",
        "cover": "http://static.hdslb.com/images/transparent.gif",
        "likes": 3,
        "hates": 1,
        "liked": 0,
        "hated": 0,
        "attribute": 0
      },
      {
        "tag_id": 3502,
        "tag_name": "空之境界",
        "cover": "http://i0.hdslb.com/bfs/tag/3751c2e985350da5a4da48e9255020e3c542eacd.jpg",
        "likes": 2,
        "hates": 0,
        "liked": 0,
        "hated": 0,
        "attribute": 0
      },
      {
        "tag_id": 2526574,
        "tag_name": "Fate/Grand Order",
        "cover": "",
        "likes": 1,
        "hates": 0,
        "liked": 0,
        "hated": 0,
        "attribute": 0
      },
      {
        "tag_id": 2917018,
        "tag_name": "王哈桑",
        "cover": "",
        "likes": 1,
        "hates": 0,
        "liked": 0,
        "hated": 0,
        "attribute": 0
      },
      {
        "tag_id": 2900828,
        "tag_name": "伪mad",
        "cover": "",
        "likes": 0,
        "hates": 0,
        "liked": 0,
        "hated": 0,
        "attribute": 0
      },
      {
        "tag_id": 4657562,
        "tag_name": "尼禄祭高难度",
        "cover": "",
        "likes": 0,
        "hates": 0,
        "liked": 0,
        "hated": 0,
        "attribute": 0
      },
      {
        "tag_id": 159994,
        "tag_name": "矛盾螺旋",
        "cover": "http://static.hdslb.com/images/transparent.gif",
        "likes": 0,
        "hates": 0,
        "liked": 0,
        "hated": 0,
        "attribute": 0
      }
    ],
    "elec": {
      "show": true,
      "total": 82,
      "count": 1,
      "elec_num": 0,
      "list": [
        {
          "pay_mid": 15683974,
          "rank": 1,
          "uname": "我欲因之梦吴越Doctor",
          "avatar": "http://i2.hdslb.com/bfs/face/3c74a56742c5bcaa05144c61c98e12b95810e35b.jpg"
        }
      ],
      "elec_set": {
        "elec_theme": 0,
        "rmb_rate": 10,
        "integrity_rate": 10,
        "round_mode": 0,
        "elec_list": [
          {
            "title": "20电池",
            "elec_num": 20,
            "is_customize": 0
          },
          {
            "title": "60电池",
            "elec_num": 60,
            "is_customize": 0
          },
          {
            "title": "450电池",
            "elec_num": 450,
            "is_customize": 0
          },
          {
            "title": "880电池",
            "elec_num": 880,
            "is_customize": 0
          },
          {
            "title": "自定义",
            "elec_num": 0,
            "is_customize": 1,
            "min_elec": 20,
            "max_elec": 99999
          }
        ]
      }
    },
    "history": {
      "cid": 0,
      "progress": 0
    },
    "ad": [
      {
        "index": 1,
        "cm_mark": 0,
        "src_id": 2030,
        "request_id": "1509079771850q172a18a61a252q282",
        "creative_id": 0,
        "creative_type": 0,
        "type": 0,
        "cover": "",
        "title": "",
        "button_title": "",
        "desc": "",
        "owner_name": "",
        "view": 0,
        "danmaku": 0,
        "is_ad": false,
        "is_ad_loc": true,
        "ad_cb": "",
        "show_url": "",
        "click_url": "",
        "client_ip": "113.119.42.121"
      }
    ],
    "relates": [
      {
        "aid": 9321222,
        "pic": "http://i1.hdslb.com/bfs/archive/86c8bfb63d2bd0b8841eb306fc43c88b5b346c08.png",
        "title": "【1080P】 空之境界 剧场版 Reminder【澄空学园&魔术师工房】",
        "owner": {
          "mid": 0,
          "name": "BlackTouma",
          "face": ""
        },
        "stat": {
          "aid": 0,
          "view": 40517,
          "danmaku": 139,
          "reply": 88,
          "favorite": 2205,
          "coin": 0,
          "share": 0,
          "now_rank": 0,
          "his_rank": 0,
          "like": 0
        }
      },
      {
        "aid": 4645841,
        "pic": "http://i2.hdslb.com/bfs/archive/d8a2cc22c3e51dbf95903cb759d1f28dd3581573.jpg",
        "title": "【Fate/空之境界】剑式之战，saber VS 两仪式，谁是你的最爱？",
        "owner": {
          "mid": 0,
          "name": "吾王之騎士",
          "face": ""
        },
        "stat": {
          "aid": 0,
          "view": 77299,
          "danmaku": 868,
          "reply": 1171,
          "favorite": 926,
          "coin": 0,
          "share": 0,
          "now_rank": 0,
          "his_rank": 0,
          "like": 0
        }
      },
      {
        "aid": 14710298,
        "pic": "http://i0.hdslb.com/bfs/archive/2c8ce8c90af344c63ad32b26c9fc60a6d9715dd2.jpg",
        "title": "【毒安利】意义深刻的史诗级狗粮巨作——空之境界",
        "owner": {
          "mid": 0,
          "name": "不会说话的xC",
          "face": ""
        },
        "stat": {
          "aid": 0,
          "view": 14498,
          "danmaku": 369,
          "reply": 291,
          "favorite": 540,
          "coin": 0,
          "share": 0,
          "now_rank": 0,
          "his_rank": 0,
          "like": 0
        }
      },
      {
        "aid": 2121458,
        "pic": "http://i0.hdslb.com/bfs/archive/2ff86363da0a2c106fd2628bac1421046177caec.jpg",
        "title": "【LexBurner】秒杀一切，两仪式弑神自封",
        "owner": {
          "mid": 0,
          "name": "LexBurner",
          "face": ""
        },
        "stat": {
          "aid": 0,
          "view": 588324,
          "danmaku": 9336,
          "reply": 760,
          "favorite": 1288,
          "coin": 0,
          "share": 0,
          "now_rank": 0,
          "his_rank": 0,
          "like": 0
        }
      },
      {
        "aid": 14208735,
        "pic": "http://i1.hdslb.com/bfs/archive/cd8d5d0c2ca04e8737fabf149fa34e01bc61fc1e.png",
        "title": "【FGO】就算是神，我也杀给你看——百级剑式单挑狮子王",
        "owner": {
          "mid": 0,
          "name": "Shiki丶_",
          "face": ""
        },
        "stat": {
          "aid": 0,
          "view": 22187,
          "danmaku": 229,
          "reply": 241,
          "favorite": 139,
          "coin": 0,
          "share": 0,
          "now_rank": 0,
          "his_rank": 0,
          "like": 0
        }
      },
      {
        "aid": 9050829,
        "pic": "http://i2.hdslb.com/bfs/archive/88e5d2015b3e596aaaacf4618fddc78499831c0b.jpg",
        "title": "【Fate/Grand Order】首次联动——空之境界震撼来袭",
        "owner": {
          "mid": 0,
          "name": "哔哩哔哩游戏中心",
          "face": ""
        },
        "stat": {
          "aid": 0,
          "view": 428304,
          "danmaku": 2059,
          "reply": 1899,
          "favorite": 5636,
          "coin": 0,
          "share": 0,
          "now_rank": 0,
          "his_rank": 0,
          "like": 0
        }
      },
      {
        "aid": 14683709,
        "pic": "http://i0.hdslb.com/bfs/archive/5ef6a51625c5256f044573da9f65d4aa4546d200.jpg",
        "title": "阿拉什的新朋友",
        "owner": {
          "mid": 0,
          "name": "大丁丁少女_",
          "face": ""
        },
        "stat": {
          "aid": 0,
          "view": 27479,
          "danmaku": 180,
          "reply": 249,
          "favorite": 100,
          "coin": 0,
          "share": 0,
          "now_rank": 0,
          "his_rank": 0,
          "like": 0
        }
      },
      {
        "aid": 7161707,
        "pic": "http://i0.hdslb.com/bfs/archive/a0ee7f438029cd770a2efc2932a7ad17e4377586.jpg",
        "title": "【梶浦由记】剧场版 空之境界 Vol.8「终章 - 空之境界」Original Sound Track",
        "owner": {
          "mid": 0,
          "name": "William潘",
          "face": ""
        },
        "stat": {
          "aid": 0,
          "view": 210103,
          "danmaku": 275,
          "reply": 402,
          "favorite": 12383,
          "coin": 0,
          "share": 0,
          "now_rank": 0,
          "his_rank": 0,
          "like": 0
        }
      },
      {
        "aid": 14747316,
        "pic": "http://i0.hdslb.com/bfs/archive/0d51cb0d75e963329a28c3e13c042dd92991acf0.jpg",
        "title": "【FGO】让你有计划地肝活动的实用APP——咕哒",
        "owner": {
          "mid": 0,
          "name": "梅加Mikaku",
          "face": ""
        },
        "stat": {
          "aid": 0,
          "view": 29424,
          "danmaku": 291,
          "reply": 170,
          "favorite": 733,
          "coin": 0,
          "share": 0,
          "now_rank": 0,
          "his_rank": 0,
          "like": 0
        }
      },
      {
        "aid": 14597364,
        "pic": "http://i2.hdslb.com/bfs/archive/c83e02b78d4d535ffa43aea8c6e76cee9a80c350.jpg",
        "title": "这42个英灵你会选择哪一个?还在选择困难么？",
        "owner": {
          "mid": 0,
          "name": "祭殁之歌",
          "face": ""
        },
        "stat": {
          "aid": 0,
          "view": 99135,
          "danmaku": 1370,
          "reply": 1831,
          "favorite": 2217,
          "coin": 0,
          "share": 0,
          "now_rank": 0,
          "his_rank": 0,
          "like": 0
        }
      },
      {
        "aid": 12482458,
        "pic": "http://i0.hdslb.com/bfs/archive/3d9f5ba5706e6bb355f05e16e520ab8af285b112.png",
        "title": "【fgo】红a无法厨力放出的泳装第二期高难度",
        "owner": {
          "mid": 0,
          "name": "竹宫悠子",
          "face": ""
        },
        "stat": {
          "aid": 0,
          "view": 10996,
          "danmaku": 347,
          "reply": 125,
          "favorite": 46,
          "coin": 0,
          "share": 0,
          "now_rank": 0,
          "his_rank": 0,
          "like": 0
        }
      },
      {
        "aid": 9216390,
        "pic": "http://i0.hdslb.com/bfs/archive/763746a0cce439369fe8bc2819d18abcd6cfb6a3.jpg",
        "title": "【文曰小强】7分钟看完《空之境界》TV版1~13集",
        "owner": {
          "mid": 0,
          "name": "文曰小强",
          "face": ""
        },
        "stat": {
          "aid": 0,
          "view": 272210,
          "danmaku": 1618,
          "reply": 1213,
          "favorite": 4666,
          "coin": 0,
          "share": 0,
          "now_rank": 0,
          "his_rank": 0,
          "like": 0
        }
      },
      {
        "aid": 14557315,
        "pic": "http://i2.hdslb.com/bfs/archive/b937b2d1799d4209a0b188c394c2ceecbed218ed.jpg",
        "title": "当王哈桑来到饥荒",
        "owner": {
          "mid": 0,
          "name": "末地or小黑",
          "face": ""
        },
        "stat": {
          "aid": 0,
          "view": 68358,
          "danmaku": 210,
          "reply": 351,
          "favorite": 837,
          "coin": 0,
          "share": 0,
          "now_rank": 0,
          "his_rank": 0,
          "like": 0
        }
      },
      {
        "aid": 14553394,
        "pic": "http://i1.hdslb.com/bfs/archive/de862284a5e3efdd3fadeb83ba6d2bc2c19b8172.jpg",
        "title": "FGO国服100级静谧的哈桑测试",
        "owner": {
          "mid": 0,
          "name": "Polyhedra0",
          "face": ""
        },
        "stat": {
          "aid": 0,
          "view": 25185,
          "danmaku": 94,
          "reply": 147,
          "favorite": 112,
          "coin": 0,
          "share": 0,
          "now_rank": 0,
          "his_rank": 0,
          "like": 0
        }
      },
      {
        "aid": 14683130,
        "pic": "http://i1.hdslb.com/bfs/archive/4c68e1df9cfa677375cf7614258c54d303bf69c5.png",
        "title": "震惊！FGO竟然会使青少年...",
        "owner": {
          "mid": 0,
          "name": "逍窑子",
          "face": ""
        },
        "stat": {
          "aid": 0,
          "view": 56604,
          "danmaku": 1705,
          "reply": 490,
          "favorite": 868,
          "coin": 0,
          "share": 0,
          "now_rank": 0,
          "his_rank": 0,
          "like": 0
        }
      },
      {
        "aid": 5179348,
        "pic": "http://i0.hdslb.com/bfs/archive/b14857baa2ddec91d47b72f6abff7d802c00b8f3.jpg",
        "title": "【弥生凛】【高燃AMV】空之境界两仪式战斗场面混剪",
        "owner": {
          "mid": 0,
          "name": "弥生凛",
          "face": ""
        },
        "stat": {
          "aid": 0,
          "view": 44524,
          "danmaku": 226,
          "reply": 157,
          "favorite": 1377,
          "coin": 0,
          "share": 0,
          "now_rank": 0,
          "his_rank": 0,
          "like": 0
        }
      },
      {
        "aid": 7997509,
        "pic": "http://i0.hdslb.com/bfs/archive/5e2f6c654d19cf32dfaefcb18867156c2d4e3bdf.jpg",
        "title": "【FGO】我王哈桑今天教你怎么玩刺客",
        "owner": {
          "mid": 0,
          "name": "非洲企鹅鹅",
          "face": ""
        },
        "stat": {
          "aid": 0,
          "view": 71460,
          "danmaku": 760,
          "reply": 259,
          "favorite": 674,
          "coin": 0,
          "share": 0,
          "now_rank": 0,
          "his_rank": 0,
          "like": 0
        }
      },
      {
        "aid": 14735577,
        "pic": "http://i1.hdslb.com/bfs/archive/ed57c5f16b76cf753a32a451ce9074621acf0269.png",
        "title": "【fgo科普】盘点那些经常被婊的画师",
        "owner": {
          "mid": 0,
          "name": "无真咖啡",
          "face": ""
        },
        "stat": {
          "aid": 0,
          "view": 79007,
          "danmaku": 1668,
          "reply": 903,
          "favorite": 1953,
          "coin": 0,
          "share": 0,
          "now_rank": 0,
          "his_rank": 0,
          "like": 0
        }
      },
      {
        "aid": 14768697,
        "pic": "http://i2.hdslb.com/bfs/archive/3e6962f2c0449f955a71c92a04855e45c3f6eeba.png",
        "title": "【FGO游戏杂谈2】咕哒子还未出手，呆毛就倒下了？！",
        "owner": {
          "mid": 0,
          "name": "小强凌凌柒",
          "face": ""
        },
        "stat": {
          "aid": 0,
          "view": 42027,
          "danmaku": 485,
          "reply": 309,
          "favorite": 391,
          "coin": 0,
          "share": 0,
          "now_rank": 0,
          "his_rank": 0,
          "like": 0
        }
      },
      {
        "aid": 14670894,
        "pic": "http://i2.hdslb.com/bfs/archive/efcf8540a7b32a0626ae4f0114408c8f9ab08f07.png",
        "title": "【FGO】为了抽礼装我花了1000个石头，为何你却给我歪出一个达芬奇（亲？）",
        "owner": {
          "mid": 0,
          "name": "油脸欢欢丶",
          "face": ""
        },
        "stat": {
          "aid": 0,
          "view": 16659,
          "danmaku": 699,
          "reply": 337,
          "favorite": 65,
          "coin": 0,
          "share": 0,
          "now_rank": 0,
          "his_rank": 0,
          "like": 0
        }
      },
      {
        "aid": 14583668,
        "pic": "http://i2.hdslb.com/bfs/archive/b43539931f1e17666e65898164e36613ab1de19f.jpg",
        "title": "某领导竟然暴打下属，竟然当着其女儿的面",
        "owner": {
          "mid": 0,
          "name": "溯夜白",
          "face": ""
        },
        "stat": {
          "aid": 0,
          "view": 32378,
          "danmaku": 108,
          "reply": 286,
          "favorite": 760,
          "coin": 0,
          "share": 0,
          "now_rank": 0,
          "his_rank": 0,
          "like": 0
        }
      },
      {
        "aid": 14709182,
        "pic": "http://i2.hdslb.com/bfs/archive/250e25fb0f2c5dda17cb62824603a66f8caaf96a.png",
        "title": "--FGO--那些fgo的图集第十五期",
        "owner": {
          "mid": 0,
          "name": "EX夏恒涵",
          "face": ""
        },
        "stat": {
          "aid": 0,
          "view": 61192,
          "danmaku": 1284,
          "reply": 271,
          "favorite": 2048,
          "coin": 0,
          "share": 0,
          "now_rank": 0,
          "his_rank": 0,
          "like": 0
        }
      },
      {
        "aid": 7455403,
        "pic": "http://i0.hdslb.com/bfs/archive/8ed0e1a6872bda7551c798cb26247f5511c54cf5.jpg",
        "title": "【Fate/Grand Order】满破・山中老人〔王哈桑〕（CV 中田让治） 宝具动画演出",
        "owner": {
          "mid": 0,
          "name": "莉莎娜",
          "face": ""
        },
        "stat": {
          "aid": 0,
          "view": 121789,
          "danmaku": 357,
          "reply": 291,
          "favorite": 1214,
          "coin": 0,
          "share": 0,
          "now_rank": 0,
          "his_rank": 0,
          "like": 0
        }
      },
      {
        "aid": 7960178,
        "pic": "http://i0.hdslb.com/bfs/archive/de866594123ac4c07028620edbd84108eea2446c.jpg",
        "title": "【FGO】无双信条——我蛤某人今天就教你怎么做刺客",
        "owner": {
          "mid": 0,
          "name": "氪金氪金氪",
          "face": ""
        },
        "stat": {
          "aid": 0,
          "view": 298959,
          "danmaku": 1696,
          "reply": 1228,
          "favorite": 2593,
          "coin": 0,
          "share": 0,
          "now_rank": 0,
          "his_rank": 0,
          "like": 0
        }
      },
      {
        "aid": 14390519,
        "pic": "http://i1.hdslb.com/bfs/archive/c6b294c71ba2ab4615ae6dbf27ea3122ce625c1b.jpg",
        "title": "【fgo】尼禄祭高难度阿拉什，流星雨和活下去",
        "owner": {
          "mid": 0,
          "name": "竹宫悠子",
          "face": ""
        },
        "stat": {
          "aid": 0,
          "view": 3790,
          "danmaku": 92,
          "reply": 36,
          "favorite": 37,
          "coin": 0,
          "share": 0,
          "now_rank": 0,
          "his_rank": 0,
          "like": 0
        }
      },
      {
        "aid": 14754646,
        "pic": "http://i2.hdslb.com/bfs/archive/f22121623d1bbcff2d7a61eff45f7c8e03782aaf.jpg",
        "title": "【FGO】1000万下载 新CM",
        "owner": {
          "mid": 0,
          "name": "_狛枝凪斗",
          "face": ""
        },
        "stat": {
          "aid": 0,
          "view": 56015,
          "danmaku": 54,
          "reply": 659,
          "favorite": 376,
          "coin": 0,
          "share": 0,
          "now_rank": 0,
          "his_rank": 0,
          "like": 0
        }
      },
      {
        "aid": 14624817,
        "pic": "http://i1.hdslb.com/bfs/archive/8cc4e1999947f5d3f31cfdd2ad4e9a3ad6f8c180.jpg",
        "title": "【全程作死】彻底玩坏Fate，第四弹",
        "owner": {
          "mid": 0,
          "name": "发癫的四叶草",
          "face": ""
        },
        "stat": {
          "aid": 0,
          "view": 247340,
          "danmaku": 7612,
          "reply": 651,
          "favorite": 11162,
          "coin": 0,
          "share": 0,
          "now_rank": 0,
          "his_rank": 0,
          "like": 0
        }
      },
      {
        "aid": 14594407,
        "pic": "http://i0.hdslb.com/bfs/archive/868ee7271a624d89259d3f29d2ebff36c84f6cd5.png",
        "title": "【FGO】国服目前最爽的黑贞暴击队",
        "owner": {
          "mid": 0,
          "name": "Anarchy2014",
          "face": ""
        },
        "stat": {
          "aid": 0,
          "view": 43924,
          "danmaku": 242,
          "reply": 326,
          "favorite": 208,
          "coin": 0,
          "share": 0,
          "now_rank": 0,
          "his_rank": 0,
          "like": 0
        }
      },
      {
        "aid": 14728627,
        "pic": "http://i0.hdslb.com/bfs/archive/919accd935dd8bcce31afe56beb71d3bac7ef48f.jpg",
        "title": "狂阶！看来孔明稳了！别拦我，我没疯啊哈哈哈！",
        "owner": {
          "mid": 0,
          "name": "NPC才是BOSS",
          "face": ""
        },
        "stat": {
          "aid": 0,
          "view": 46197,
          "danmaku": 712,
          "reply": 569,
          "favorite": 102,
          "coin": 0,
          "share": 0,
          "now_rank": 0,
          "his_rank": 0,
          "like": 0
        }
      },
      {
        "aid": 15449860,
        "pic": "http://i0.hdslb.com/bfs/archive/563a4094cc3bee68503bf3e6ce9f117c214043c6.jpg",
        "title": "式姐百级达成留恋，我可能是国服第一（倒数）个百级式姐了",
        "owner": {
          "mid": 0,
          "name": "サトシ忍者蛙",
          "face": ""
        },
        "stat": {
          "aid": 0,
          "view": 6206,
          "danmaku": 34,
          "reply": 193,
          "favorite": 64,
          "coin": 0,
          "share": 0,
          "now_rank": 0,
          "his_rank": 0,
          "like": 0
        }
      },
      {
        "aid": 14741578,
        "pic": "http://i2.hdslb.com/bfs/archive/66ea8f2fb61ef4f920b14381c67162306789bf4c.jpg",
        "title": "【FGO】当三发单抽出了最强巴萨卡，然而UP主却拍烂了桌子...",
        "owner": {
          "mid": 0,
          "name": "叶落间愁",
          "face": ""
        },
        "stat": {
          "aid": 0,
          "view": 69410,
          "danmaku": 748,
          "reply": 490,
          "favorite": 118,
          "coin": 0,
          "share": 0,
          "now_rank": 0,
          "his_rank": 0,
          "like": 0
        }
      },
      {
        "aid": 15482872,
        "pic": "http://i0.hdslb.com/bfs/archive/cef11d7c4ced88e1ce5eeda6eea02339fd161903.jpg",
        "title": "【FGO】迦勒底的温馨日常",
        "owner": {
          "mid": 0,
          "name": "谍报EX的红茶",
          "face": ""
        },
        "stat": {
          "aid": 0,
          "view": 43479,
          "danmaku": 405,
          "reply": 171,
          "favorite": 3953,
          "coin": 0,
          "share": 0,
          "now_rank": 0,
          "his_rank": 0,
          "like": 0
        }
      },
      {
        "aid": 14668018,
        "pic": "http://i0.hdslb.com/bfs/archive/9004f8396221a8d530dcdffc2de293ea80128e2e.jpg",
        "title": "【Fate/Grand Order】室友的福袋，真是羡慕死我了······",
        "owner": {
          "mid": 0,
          "name": "死宅占领世界",
          "face": ""
        },
        "stat": {
          "aid": 0,
          "view": 25219,
          "danmaku": 314,
          "reply": 261,
          "favorite": 66,
          "coin": 0,
          "share": 0,
          "now_rank": 0,
          "his_rank": 0,
          "like": 0
        }
      },
      {
        "aid": 8328852,
        "pic": "http://i1.hdslb.com/bfs/archive/c3e308f0f60666e38be489647a4102fb63373674.jpg",
        "title": "王哈桑单骑挑战巖窟王",
        "owner": {
          "mid": 0,
          "name": "菜死你不偿命",
          "face": ""
        },
        "stat": {
          "aid": 0,
          "view": 43367,
          "danmaku": 692,
          "reply": 241,
          "favorite": 508,
          "coin": 0,
          "share": 0,
          "now_rank": 0,
          "his_rank": 0,
          "like": 0
        }
      },
      {
        "aid": 14043214,
        "pic": "http://i0.hdslb.com/bfs/archive/aaa36cc90ab0665afbc5a23d1a15e59ef11a6b92.png",
        "title": "【FGO】泳装尼禄唱歌3分钟循环",
        "owner": {
          "mid": 0,
          "name": "神枪·深红",
          "face": ""
        },
        "stat": {
          "aid": 0,
          "view": 136475,
          "danmaku": 586,
          "reply": 437,
          "favorite": 4724,
          "coin": 0,
          "share": 0,
          "now_rank": 0,
          "his_rank": 0,
          "like": 0
        }
      },
      {
        "aid": 9181013,
        "pic": "http://i0.hdslb.com/bfs/archive/fe907fcac9f5ff4126d3ba4d4d80480e87090bf9.jpg",
        "title": "【FGO】轮到两仪式来给你洗脑了~",
        "owner": {
          "mid": 0,
          "name": "丸子",
          "face": ""
        },
        "stat": {
          "aid": 0,
          "view": 311738,
          "danmaku": 2101,
          "reply": 1411,
          "favorite": 5440,
          "coin": 0,
          "share": 0,
          "now_rank": 0,
          "his_rank": 0,
          "like": 0
        }
      },
      {
        "aid": 14630152,
        "pic": "http://i2.hdslb.com/bfs/archive/2792b8478e9d3b4a4a1ee2d19ea14f8df6c56949.jpg",
        "title": "【FGO】尼禄唱歌真好听！",
        "owner": {
          "mid": 0,
          "name": "乔玄乔斯达",
          "face": ""
        },
        "stat": {
          "aid": 0,
          "view": 96503,
          "danmaku": 604,
          "reply": 318,
          "favorite": 1575,
          "coin": 0,
          "share": 0,
          "now_rank": 0,
          "his_rank": 0,
          "like": 0
        }
      },
      {
        "aid": 14541752,
        "pic": "http://i2.hdslb.com/bfs/archive/d826b86ec10c8974bd2b86f269a415434df5eef5.jpg",
        "title": "【FGO】崔悲伤：“想不到吧，我走出迷宫了！！！”",
        "owner": {
          "mid": 0,
          "name": "遗失的拼图",
          "face": ""
        },
        "stat": {
          "aid": 0,
          "view": 28328,
          "danmaku": 303,
          "reply": 270,
          "favorite": 186,
          "coin": 0,
          "share": 0,
          "now_rank": 0,
          "his_rank": 0,
          "like": 0
        }
      },
      {
        "aid": 14576604,
        "pic": "http://i0.hdslb.com/bfs/archive/fe5bff95f2017c6a0ef470853eb6c447d2dde5e3.png",
        "title": "【百级李大师单挑】又到了那收割闪闪的季节",
        "owner": {
          "mid": 0,
          "name": "传说中的绿拐",
          "face": ""
        },
        "stat": {
          "aid": 0,
          "view": 10982,
          "danmaku": 132,
          "reply": 111,
          "favorite": 48,
          "coin": 0,
          "share": 0,
          "now_rank": 0,
          "his_rank": 0,
          "like": 0
        }
      },
      {
        "aid": 14601254,
        "pic": "http://i1.hdslb.com/bfs/archive/24f13832b53a76abcac266794cb9f51a80ce608e.png",
        "title": "【FGO】梅林非要我唱歌！呆毛听了想打人！",
        "owner": {
          "mid": 0,
          "name": "丸子",
          "face": ""
        },
        "stat": {
          "aid": 0,
          "view": 77611,
          "danmaku": 3137,
          "reply": 490,
          "favorite": 1770,
          "coin": 0,
          "share": 0,
          "now_rank": 0,
          "his_rank": 0,
          "like": 0
        }
      }
    ],
    "dislike_reasons": [
      {
        "reason_id": 5,
        "reason_name": "标题党/封面党"
      },
      {
        "reason_id": 6,
        "reason_name": "内容质量差"
      },
      {
        "reason_id": 7,
        "reason_name": "内容/封面令人不适"
      },
      {
        "reason_id": 8,
        "reason_name": "营销广告"
      }
    ]
  },
  "message": "0",
  "ttl": 1
}
